{
  "version": 1,
  "entries": [
    {
      "snapshot": "examples/01-discovery-completed",
      "skillFiles": [
        {
          "path": "skills/amadeus-steering/SKILL.md",
          "md5": "b05111b434618fc9f361e907760d6976",
          "staleReason": "Steering 詳細成果物を steering/ 配下へ移す構造契約を反映したため。後続 PR で real provider による再生成を実施する。"
        },
        {
          "path": "skills/amadeus-discovery/SKILL.md",
          "md5": "143ade919ecaf01fe05de22f7597949e",
          "staleReason": "Grilling Decision Trail の skill 規約だけを更新し、既存 example は migration 対象外のため。"
        }
      ]
    },
    {
      "snapshot": "examples/02-intent-initialized",
      "skillFiles": [
        {
          "path": "skills/amadeus-steering/SKILL.md",
          "md5": "b05111b434618fc9f361e907760d6976",
          "staleReason": "Steering 詳細成果物を steering/ 配下へ移す構造契約を反映したため。後続 PR で real provider による再生成を実施する。"
        },
        {
          "path": "skills/amadeus-discovery/SKILL.md",
          "md5": "143ade919ecaf01fe05de22f7597949e",
          "staleReason": "Grilling Decision Trail の skill 規約だけを更新し、既存 example は migration 対象外のため。"
        },
        {
          "path": "skills/amadeus-intent-init/SKILL.md",
          "md5": "0a7e5c285c49edfd126fa53e9911cac9",
          "staleReason": "Grilling Decision Trail の skill 規約だけを更新し、既存 example は migration 対象外のため。"
        }
      ]
    },
    {
      "snapshot": "examples/03-ideation-completed",
      "skillFiles": [
        {
          "path": "skills/amadeus-steering/SKILL.md",
          "md5": "b05111b434618fc9f361e907760d6976",
          "staleReason": "Steering 詳細成果物を steering/ 配下へ移す構造契約を反映したため。後続 PR で real provider による再生成を実施する。"
        },
        {
          "path": "skills/amadeus-discovery/SKILL.md",
          "md5": "143ade919ecaf01fe05de22f7597949e",
          "staleReason": "Grilling Decision Trail の skill 規約だけを更新し、既存 example は migration 対象外のため。"
        },
        {
          "path": "skills/amadeus-intent-init/SKILL.md",
          "md5": "0a7e5c285c49edfd126fa53e9911cac9",
          "staleReason": "Grilling Decision Trail の skill 規約だけを更新し、既存 example は migration 対象外のため。"
        },
        {
          "path": "skills/amadeus-ideation/SKILL.md",
          "md5": "f5b26b6fa308736ae29518b4745ef89a"
        },
        {
          "path": "skills/amadeus-ideation-scope-framing/SKILL.md",
          "md5": "f45a03df7d62a7c4d4413601d7abe813"
        },
        {
          "path": "skills/amadeus-ideation-feasibility-shaping/SKILL.md",
          "md5": "173108e791b6f44695675aaedba2f65e"
        },
        {
          "path": "skills/amadeus-ideation-mock-framing/SKILL.md",
          "md5": "fb13e538559b5f1d23c756e7ca9d6446"
        },
        {
          "path": "skills/amadeus-ideation-traceability-finalization/SKILL.md",
          "md5": "823dd45d5c795cf8e421f7f7b5a6f746"
        }
      ]
    },
    {
      "snapshot": "examples/04-inception-completed",
      "skillFiles": [
        {
          "path": "skills/amadeus-steering/SKILL.md",
          "md5": "b05111b434618fc9f361e907760d6976",
          "staleReason": "Steering 詳細成果物を steering/ 配下へ移す構造契約を反映したため。後続 PR で real provider による再生成を実施する。"
        },
        {
          "path": "skills/amadeus-discovery/SKILL.md",
          "md5": "143ade919ecaf01fe05de22f7597949e",
          "staleReason": "Grilling Decision Trail の skill 規約だけを更新し、既存 example は migration 対象外のため。"
        },
        {
          "path": "skills/amadeus-intent-init/SKILL.md",
          "md5": "0a7e5c285c49edfd126fa53e9911cac9",
          "staleReason": "Grilling Decision Trail の skill 規約だけを更新し、既存 example は migration 対象外のため。"
        },
        {
          "path": "skills/amadeus-ideation/SKILL.md",
          "md5": "f5b26b6fa308736ae29518b4745ef89a"
        },
        {
          "path": "skills/amadeus-ideation-scope-framing/SKILL.md",
          "md5": "f45a03df7d62a7c4d4413601d7abe813"
        },
        {
          "path": "skills/amadeus-ideation-feasibility-shaping/SKILL.md",
          "md5": "173108e791b6f44695675aaedba2f65e"
        },
        {
          "path": "skills/amadeus-ideation-mock-framing/SKILL.md",
          "md5": "fb13e538559b5f1d23c756e7ca9d6446"
        },
        {
          "path": "skills/amadeus-ideation-traceability-finalization/SKILL.md",
          "md5": "823dd45d5c795cf8e421f7f7b5a6f746"
        },
        {
          "path": "skills/amadeus-inception/SKILL.md",
          "md5": "a945f2cac547a8260750fcd9f2c1fe50"
        },
        {
          "path": "skills/amadeus-inception-requirements-definition/SKILL.md",
          "md5": "d09368bbc1eba9fbf3b945a1b43db201"
        },
        {
          "path": "skills/amadeus-inception-interaction-modeling/SKILL.md",
          "md5": "1737e758d0bfd60306b4ef196f3a7abb"
        },
        {
          "path": "skills/amadeus-inception-execution-design/SKILL.md",
          "md5": "24bd5abff841ca019e4cb80984eb324d"
        },
        {
          "path": "skills/amadeus-inception-traceability-finalization/SKILL.md",
          "md5": "397d5e61ef5ade898b0c696035ee4d4e"
        }
      ]
    },
    {
      "snapshot": "examples/05-construction-design-ready",
      "skillFiles": [
        {
          "path": "skills/amadeus-steering/SKILL.md",
          "md5": "b05111b434618fc9f361e907760d6976",
          "staleReason": "Steering 詳細成果物を steering/ 配下へ移す構造契約を反映したため。後続 PR で real provider による再生成を実施する。"
        },
        {
          "path": "skills/amadeus-discovery/SKILL.md",
          "md5": "143ade919ecaf01fe05de22f7597949e",
          "staleReason": "Grilling Decision Trail の skill 規約だけを更新し、既存 example は migration 対象外のため。"
        },
        {
          "path": "skills/amadeus-intent-init/SKILL.md",
          "md5": "0a7e5c285c49edfd126fa53e9911cac9",
          "staleReason": "Grilling Decision Trail の skill 規約だけを更新し、既存 example は migration 対象外のため。"
        },
        {
          "path": "skills/amadeus-ideation/SKILL.md",
          "md5": "f5b26b6fa308736ae29518b4745ef89a"
        },
        {
          "path": "skills/amadeus-ideation-scope-framing/SKILL.md",
          "md5": "f45a03df7d62a7c4d4413601d7abe813"
        },
        {
          "path": "skills/amadeus-ideation-feasibility-shaping/SKILL.md",
          "md5": "173108e791b6f44695675aaedba2f65e"
        },
        {
          "path": "skills/amadeus-ideation-mock-framing/SKILL.md",
          "md5": "fb13e538559b5f1d23c756e7ca9d6446"
        },
        {
          "path": "skills/amadeus-ideation-traceability-finalization/SKILL.md",
          "md5": "823dd45d5c795cf8e421f7f7b5a6f746"
        },
        {
          "path": "skills/amadeus-inception/SKILL.md",
          "md5": "a945f2cac547a8260750fcd9f2c1fe50"
        },
        {
          "path": "skills/amadeus-inception-requirements-definition/SKILL.md",
          "md5": "d09368bbc1eba9fbf3b945a1b43db201"
        },
        {
          "path": "skills/amadeus-inception-interaction-modeling/SKILL.md",
          "md5": "1737e758d0bfd60306b4ef196f3a7abb"
        },
        {
          "path": "skills/amadeus-inception-execution-design/SKILL.md",
          "md5": "24bd5abff841ca019e4cb80984eb324d"
        },
        {
          "path": "skills/amadeus-inception-traceability-finalization/SKILL.md",
          "md5": "397d5e61ef5ade898b0c696035ee4d4e"
        },
        {
          "path": "skills/amadeus-construction-bolt-preparation/SKILL.md",
          "md5": "f048f78d0290221b764a43e08c98772e"
        }
      ]
    }
  ]
}
